petdb/__init__.py
petdb/pcollection.py
petdb/pdb.py
petdb/pexceptions.py
petdb/putils.py
petdb/service/__init__.py
petdb/service/__main__.py
petdb/service/api.py
petdb/service/pcollection.py
petdb/service/pdb.py
petdb/service/server.py
petdb-0.10.2.dist-info/licenses/LICENSE
petdb-0.10.2.dist-info/METADATA
petdb-0.10.2.dist-info/WHEEL
petdb-0.10.2.dist-info/top_level.txt
petdb-0.10.2.dist-info/RECORD
