Metadata-Version: 2.4
Name: petdb
Version: 0.10.2
Summary: Light weight local document-oriented database
Author-email: Maks Vinnytskyi <ownerofforest@gmail.com>
Project-URL: Homepage, https://gitlab.com/Tullp/petdb
Classifier: Programming Language :: Python :: 3.12
Classifier: License :: OSI Approved :: MIT License
Classifier: Operating System :: OS Independent
Requires-Python: >=3.12
License-File: LICENSE
Provides-Extra: service
Requires-Dist: fastapi==0.111.0; extra == "service"
Requires-Dist: petcmd; extra == "service"
Requires-Dist: requests; extra == "service"
Dynamic: license-file
